celery_dashboard/__init__.py
celery_dashboard/auth.py
celery_dashboard/cleaning.py
celery_dashboard/command.py
celery_dashboard/models.py
celery_dashboard/signals.py
celery_dashboard/utils.py
celery_dashboard/api/__init__.py
celery_dashboard/api/api.py
celery_dashboard/api/app.py
celery_dashboard/api/static.py
celery_dashboard/api/frontend/dist/index.html
celery_dashboard/api/frontend/dist/static/css/app.e7d61abb15ed5fba7eb00000f752a78d.css
celery_dashboard/api/frontend/dist/static/css/app.e7d61abb15ed5fba7eb00000f752a78d.css.map
celery_dashboard/api/frontend/dist/static/js/app.0819a7306967cc5da9ba.js
celery_dashboard/api/frontend/dist/static/js/app.0819a7306967cc5da9ba.js.map
celery_dashboard/api/frontend/dist/static/js/manifest.209a95d039575aa222e1.js
celery_dashboard/api/frontend/dist/static/js/manifest.209a95d039575aa222e1.js.map
celery_dashboard/api/frontend/dist/static/js/vendor.80e7399540a49ab1e222.js
celery_dashboard/api/frontend/dist/static/js/vendor.80e7399540a49ab1e222.js.map
celery_dashboard-0.0.1.dist-info/LICENSE
celery_dashboard-0.0.1.dist-info/METADATA
celery_dashboard-0.0.1.dist-info/WHEEL
celery_dashboard-0.0.1.dist-info/entry_points.txt
celery_dashboard-0.0.1.dist-info/top_level.txt
celery_dashboard-0.0.1.dist-info/RECORD
